mbbank/__init__.py
mbbank/capcha_ocr.py
mbbank/main.py
mbbank/mbasync.py
mbbank/modals/__init__.py
mbbank/modals/account_by_phone.py
mbbank/modals/balance.py
mbbank/modals/balance_loyalty.py
mbbank/modals/bank_list.py
mbbank/modals/base.py
mbbank/modals/beneficiary_list.py
mbbank/modals/card_list.py
mbbank/modals/card_transactions.py
mbbank/modals/interest_rate.py
mbbank/modals/loan_list.py
mbbank/modals/saving_detail.py
mbbank/modals/saving_list.py
mbbank/modals/transaction_history.py
mbbank/modals/userinfo.py
mbbank/wasm_helper/__init__.py
mbbank/wasm_helper/helper.py
mbbank_lib-0.2.7.dist-info/licenses/LICENSE.txt
mbbank_lib-0.2.7.dist-info/METADATA
mbbank_lib-0.2.7.dist-info/WHEEL
mbbank_lib-0.2.7.dist-info/top_level.txt
mbbank_lib-0.2.7.dist-info/RECORD
