Metadata-Version: 2.4
Name: mbbank-lib
Version: 0.2.7
Summary: A unofficially light weight Python Api for the "Military Commercial Joint Stock Bank" personal accounts
Home-page: https://github.com/thedtvn/MBBank
Author: The DT
License: MIT
License-File: LICENSE.txt
Requires-Dist: Pillow
Requires-Dist: requests
Requires-Dist: aiohttp
Requires-Dist: setuptools
Requires-Dist: wheel
Requires-Dist: wasmtime
Requires-Dist: mb-capcha-ocr
Requires-Dist: pydantic
Dynamic: author
Dynamic: description
Dynamic: description-content-type
Dynamic: home-page
Dynamic: license
Dynamic: license-file
Dynamic: requires-dist
Dynamic: summary
